falkordb_bulk_loader/__init__.py
falkordb_bulk_loader/bulk_insert.py
falkordb_bulk_loader/bulk_update.py
falkordb_bulk_loader/config.py
falkordb_bulk_loader/entity_file.py
falkordb_bulk_loader/exceptions.py
falkordb_bulk_loader/label.py
falkordb_bulk_loader/query_buffer.py
falkordb_bulk_loader/relation_type.py
falkordb_bulk_loader-1.0.7.dist-info/LICENSE
falkordb_bulk_loader-1.0.7.dist-info/METADATA
falkordb_bulk_loader-1.0.7.dist-info/WHEEL
falkordb_bulk_loader-1.0.7.dist-info/entry_points.txt
falkordb_bulk_loader-1.0.7.dist-info/RECORD
