Metadata-Version: 2.3
Name: falkordb-bulk-loader
Version: 1.0.7
Summary: falkordb Bulk Import Tool
License: BSD-3-Clause
Keywords: FalkorDB Graph
Author: FalkorDB Inc
Author-email: info@falkordb.com
Requires-Python: >=3.10,<4.0
Classifier: Development Status :: 5 - Production/Stable
Classifier: Intended Audience :: Developers
Classifier: License :: OSI Approved :: BSD License
Classifier: License :: OSI Approved :: MIT License
Classifier: Programming Language :: Python
Classifier: Programming Language :: Python :: 3
Classifier: Programming Language :: Python :: 3.10
Classifier: Programming Language :: Python :: 3.11
Classifier: Programming Language :: Python :: 3.12
Classifier: Programming Language :: Python :: 3.13
Classifier: Topic :: Database
Requires-Dist: FalkorDB (>=1.0.10,<2.0.0)
Requires-Dist: click (>=8.0.1,<9.0.0)
Requires-Dist: pathos (>=0.2.8,<0.3.0)
Project-URL: repository, https://github.com/falkordb/falkordb-bulk-loader
Project-URL: url, https://falkordb.com
